<?xml version="1.0" encoding="utf-8"?>
<!DOCTYPE hibernate-mapping PUBLIC "-//Hibernate/Hibernate Mapping DTD 3.0//EN"
"http://hibernate.sourceforge.net/hibernate-mapping-3.0.dtd">
<!-- Mapping file autogenerated by MyEclipse Persistence Tools -->
<hibernate-mapping>
	<class name="com.caeit.vo.Task" select-before-update="true" table="PTP_TASK" schema="PTP">
		<id name="id" column="ID" type="long">
			<generator class="native">
				<param name="sequence">TASK_ID_SEQ</param>
			</generator>
		</id>
		<property name="pid" type="long">
			<column name="PID" precision="22" scale="0" not-null="true">
				<comment>父ID，用于构建任务树</comment>
			</column>
		</property>
		<property name="planId" type="long">
			<column name="PLAN_ID" precision="22" scale="0" not-null="true">
				<comment>所属计划ID</comment>
			</column>
		</property>
		<property name="name" type="string">
			<column name="NAME" length="400" not-null="true">
				<comment>任务名称</comment>
			</column>
		</property>
		<property name="detail" type="string">
			<column name="DETAIL" length="4000" not-null="true">
				<comment>任务描述</comment>
			</column>
		</property>
		<property name="startDate" type="string">
			<column name="START_DATE" length="10" not-null="true">
				<comment>任务开始日期</comment>
			</column>
		</property>
		<property name="endDate" type="string">
			<column name="END_DATE" length="10" not-null="true">
				<comment>任务结束日期</comment>
			</column>
		</property>
		<property name="percentage" type="long">
			<column name="PERCENTAGE" precision="22" scale="0" not-null="true">
				<comment>任务完成百分比</comment>
			</column>
		</property>
		<property name="finished" type="character">
			<column name="FINISHED" length="1" not-null="true">
				<comment>任务是否完成（是为Y否为F，默认为F，当为Y时，任务完成百分比为100%）</comment>
			</column>
		</property>
	</class>
</hibernate-mapping>
